Workbook

Sheet Clean Table
A1: Transaction ID | B1: Date | C1: Description | D1: Category | E1: Subcategory | F1: Type | G1: Amount | H1: Account | I1: Payment Method | J1: Merchant
A2: TXN103021 | B2: 45658 | C2: Lidl - Restaurants | D2: Food | E2: Restaurants | F2: Expense | G2: 28.24 | H2: Main Bank | I2: Direct Debit | J2: Lidl
A3: TXN102377 | B3: 45658 | C3: EDEKA - Restaurants | D3: Food | E3: Restaurants | F3: Expense | G3: 88.87 | H3: Revolut | I3: Debit Card | J3: EDEKA
A4: TXN102040 | B4: 45658 | C4: Lidl - Groceries | D4: Food | E4: Groceries | F4: Expense | G4: 43.48 | H4: Revolut | I4: Debit Card | J4: Lidl
A5: TXN101552 | B5: 45658 | C5: Spotify - Streaming | D5: Entertainment | E5: Streaming | F5: Expense | G5: 16.27 | H5: Main Bank | I5: Debit Card | J5: Spotify
A6: TXN102049 | B6: 45658 | C6: Zalando - Household | D6: Shopping | E6: Household | F6: Expense | G6: 227.62 | H6: Main Bank | I6: Bank Transfer | J6: Zalando
A7: TXN102938 | B7: 45658 | C7: Amazon - Clothing | D7: Shopping | E7: Clothing | F7: Expense | G7: 149.75 | H7: Main Bank | I7: Direct Debit | J7: Amazon
A8: TXN102814 | B8: 45658 | C8: McDonald's - Groceries | D8: Food | E8: Groceries | F8: Expense | G8: 28.1 | H8: Revolut | I8: Debit Card | J8: McDonald's
A9: TXN100601 | B9: 45659 | C9: Local Restaurant - Restaurants | D9: Food | E9: Restaurants | F9: Expense | G9: 34.53 | H9: Main Bank | I9: Credit Card | J9: Local Restaurant
A10: TXN101261 | B10: 45659 | C10: McDonald's - Takeaway | D10: Food | E10: Takeaway | F10: Expense | G10: 52.53 | H10: Main Bank | I10: Credit Card | J10: McDonald's
A11: TXN100428 | B11: 45659 | C11: Employer Bonus - Bonus | D11: Income | E11: Bonus | F11: Income | G11: 736.64 | H11: Main Bank | I11: Bank Transfer | J11: Employer Bonus
A12: TXN100926 | B12: 45659 | C12: Landlord - Internet | D12: Housing | E12: Internet | F12: Expense | G12: 129.87 | H12: Revolut | I12: Debit Card | J12: Landlord
A13: TXN100575 | B13: 45659 | C13: Freelance Client - Freelance | D13: Income | E13: Freelance | F13: Income | G13: 377.48 | H13: Main Bank | I13: Bank Transfer | J13: Freelance Client
... A3501: TXN101600 | B3501: 46295 | C3501: Employer Bonus - Freelance | D3501: Income | E3501: Freelance | F3501: Income | G3501: 376.97 | H3501: Main Bank | I3501: Debit Card | J3501: Employer Bonus

Sheet Analysis
B4: Personal Finance — KPI Analysis | C4: Value | D4: What it measures
B6: Total Income | C6: =SUMIFS(raw_table_[Amount],raw_table_[Type],"Income") -> 817176.78 | D6: All income transactions
B8: Total Expenses | C8: =SUMIFS(raw_table_[Amount],raw_table_[Type],"Expense") -> 368935.91 | D8: All expense transactions
B10: Net Savings | C10: =C6-C8 -> 448240.87 | D10: Income minus expenses
B12: Savings Rate | C12: =C10/C6 -> 0.54852375 | D12: Savings as a share of income
B14: Total Transactions | C14: =COUNTA(raw_table_[Transaction ID]) -> 3500 | D14: Number of transactions
B16: Average Expense | C16: =AVERAGEIFS(raw_table_[Amount],raw_table_[Type],"Expense") -> 131.66878 | D16: Average expense transaction
B18: Highest Expense | C18: =_xlfn.MAXIFS(raw_table_[Amount],raw_table_[Type],"Expense") -> 1107.76 | D18: Largest expense transaction
B20: Total Expense Categories | C20: 7 | D20: Distinct expense categories
B22: Income-to-Expense Ratio | C22: =C6/C8 -> 2.2149559 | D22: Income per $1 spent

Sheet Raw_Data
A1: Transaction_ID | B1: Date | C1: Description | D1: Category | E1: Subcategory | F1: Type | G1: Amount | H1: Account | I1: Payment_Method | J1: Merchant
A2: TXN103021 | B2: 45658 | C2: Lidl - Restaurants | D2: Food | E2: Restaurants | F2: Expense | G2: 28.24 | H2: Main Bank | I2: Direct Debit | J2: Lidl
A3: TXN102377 | B3: 45658 | C3: EDEKA - Restaurants | D3: Food | E3: Restaurants | F3: Expense | G3: 88.87 | H3: Revolut | I3: Debit Card | J3: EDEKA
A4: TXN102040 | B4: 45658 | C4: Lidl - Groceries | D4: Food | E4: Groceries | F4: Expense | G4: 43.48 | H4: Revolut | I4: Debit Card | J4: Lidl
A5: TXN101552 | B5: 45658 | C5: Spotify - Streaming | D5: Entertainment | E5: Streaming | F5: Expense | G5: 16.27 | H5: Main Bank | I5: Debit Card | J5: Spotify
A6: TXN102049 | B6: 45658 | C6: Zalando - Household | D6: Shopping | E6: Household | F6: Expense | G6: 227.62 | H6: Main Bank | I6: Bank Transfer | J6: Zalando
A7: TXN102938 | B7: 45658 | C7: Amazon - Clothing | D7: Shopping | E7: Clothing | F7: Expense | G7: 149.75 | H7: Main Bank | I7: Direct Debit | J7: Amazon
A8: TXN102814 | B8: 45658 | C8: McDonald's - Groceries | D8: Food | E8: Groceries | F8: Expense | G8: 28.1 | H8: Revolut | I8: Debit Card | J8: McDonald's
A9: TXN100601 | B9: 45659 | C9: Local Restaurant - Restaurants | D9: Food | E9: Restaurants | F9: Expense | G9: 34.53 | H9: Main Bank | I9: Credit Card | J9: Local Restaurant
A10: TXN101261 | B10: 45659 | C10: McDonald's - Takeaway | D10: Food | E10: Takeaway | F10: Expense | G10: 52.53 | H10: Main Bank | I10: Credit Card | J10: McDonald's
A11: TXN100428 | B11: 45659 | C11: Employer Bonus - Bonus | D11: Income | E11: Bonus | F11: Income | G11: 736.64 | H11: Main Bank | I11: Bank Transfer | J11: Employer Bonus
A12: TXN100926 | B12: 45659 | C12: Landlord - Internet | D12: Housing | E12: Internet | F12: Expense | G12: 129.87 | H12: Revolut | I12: Debit Card | J12: Landlord
A13: TXN100575 | B13: 45659 | C13: Freelance Client - Freelance | D13: Income | E13: Freelance | F13: Income | G13: 377.48 | H13: Main Bank | I13: Bank Transfer | J13: Freelance Client
... A3501: TXN101600 | B3501: 46295 | C3501: Employer Bonus - Freelance | D3501: Income | E3501: Freelance | F3501: Income | G3501: 376.97 | H3501: Main Bank | I3501: Debit Card | J3501: Employer Bonus

Sheet Monthly Analysis
B3: Monthly Amount | C3: Column Labels | I3: 1. Which month had the highest income?
B4: Years/Months | C4: Expense | D4: Income | E4: Total | F4: Net Savings | G4: Savings Rate | I4: August 2025 recorded the highest monthly income in 2025 ($54,924), while April 2026 led the available 2026 months ($60,915).
B5: 2025 | C5: 206434.55 | D5: 462956.61 | E5: 669391.16 | F5: =D5-C5 -> 256522.06 | G5: =F5/D5 -> 0.55409525 | I5: 2. Which month had the highest expenses?
B6: Jan | C6: 17171.99 | D6: 35995.99 | E6: 53167.98 | F6: =D6-C6 -> 18824 | G6: =F6/D6 -> 0.52294714 | I6: May 2025 had the highest expenses in 2025 ($23,432), while August 2026 had the highest expenses among the available 2026 months ($22,916).
B7: Feb | C7: 14154.3 | D7: 37745.58 | E7: 51899.88 | F7: =D7-C7 -> 23591.28 | G7: =F7/D7 -> 0.62500775 | I7: 3. Which month had the highest net savings?
B8: Mar | C8: 15817.19 | D8: 48239.67 | E8: 64056.86 | F8: =D8-C8 -> 32422.48 | G8: =F8/D8 -> 0.67211239 | I8: August 2025 led 2025 ($36,633), while April 2026 led the available 2026 months ($41,619).
B9: Apr | C9: 17515.73 | D9: 28728.31 | E9: 46244.04 | F9: =D9-C9 -> 11212.58 | G9: =F9/D9 -> 0.39029724 | I9: 4. Which month had the lowest savings rate?
B10: May | C10: 23431.53 | D10: 46689.01 | E10: 70120.54 | F10: =D10-C10 -> 23257.48 | G10: =F10/D10 -> 0.49813607 | I10: October 2025 had the lowest monthly savings rate in 2025 (35.15%), while September 2026 was lowest among the available 2026 months (37.05%).
B11: Jun | C11: 14547.26 | D11: 33246.76 | E11: 47794.02 | F11: =D11-C11 -> 18699.5 | G11: =F11/D11 -> 0.56244578
B12: Jul | C12: 18124.39 | D12: 33853.41 | E12: 51977.8 | F12: =D12-C12 -> 15729.02 | G12: =F12/D12 -> 0.46462144
B13: Aug | C13: 18291.59 | D13: 54924.19 | E13: 73215.78 | F13: =D13-C13 -> 36632.6 | G13: =F13/D13 -> 0.6669666
B14: Sep | C14: 17912.45 | D14: 37130.53 | E14: 55042.98 | F14: =D14-C14 -> 19218.08 | G14: =F14/D14 -> 0.51758162
B15: Oct | C15: 18396.35 | D15: 28369.59 | E15: 46765.94 | F15: =D15-C15 -> 9973.24 | G15: =F15/D15 -> 0.35154685
B16: Nov | C16: 18523.36 | D16: 29201.79 | E16: 47725.15 | F16: =D16-C16 -> 10678.43 | G16: =F16/D16 -> 0.36567724
B17: Dec | C17: 12548.41 | D17: 48831.78 | E17: 61380.19 | F17: =D17-C17 -> 36283.37 | G17: =F17/D17 -> 0.7430278 | Z17: Month-Year | AA17: Expenses | AB17: Income
B18: 2026 | C18: 162501.36 | D18: 354220.17 | E18: 516721.53 | F18: =D18-C18 -> 191718.81 | G18: =F18/D18 -> 0.54124193 | Z18: 45658 | AA18: 17171.99 | AB18: 35995.99
B19: Jan | C19: 14793.19 | D19: 45934.13 | E19: 60727.32 | F19: =D19-C19 -> 31140.94 | G19: =F19/D19 -> 0.67794775 | Z19: 45689 | AA19: 14154.3 | AB19: 37745.58
B20: Feb | C20: 17780.67 | D20: 33306.83 | E20: 51087.5 | F20: =D20-C20 -> 15526.16 | G20: =F20/D20 -> 0.46615544 | Z20: 45717 | AA20: 15817.19 | AB20: 48239.67
B21: Mar | C21: 18342.59 | D21: 38487.05 | E21: 56829.64 | F21: =D21-C21 -> 20144.46 | G21: =F21/D21 -> 0.52340878 | Z21: 45748 | AA21: 17515.73 | AB21: 28728.31
B22: Apr | C22: 19296.2 | D22: 60915.08 | E22: 80211.28 | F22: =D22-C22 -> 41618.88 | G22: =F22/D22 -> 0.68322786 | Z22: 45778 | AA22: 23431.53 | AB22: 46689.01
B23: May | C23: 17758.06 | D23: 28961.45 | E23: 46719.51 | F23: =D23-C23 -> 11203.39 | G23: =F23/D23 -> 0.38683802 | Z23: 45809 | AA23: 14547.26 | AB23: 33246.76
B24: Jun | C24: 14106.98 | D24: 35508.62 | E24: 49615.6 | F24: =D24-C24 -> 21401.64 | G24: =F24/D24 -> 0.60271675 | Z24: 45839 | AA24: 18124.39 | AB24: 33853.41
B25: Jul | C25: 18351.9 | D25: 40168.51 | E25: 58520.41 | F25: =D25-C25 -> 21816.61 | G25: =F25/D25 -> 0.54312719 | Z25: 45870 | AA25: 18291.59 | AB25: 54924.19
B26: Aug | C26: 22915.77 | D26: 40506.92 | E26: 63422.69 | F26: =D26-C26 -> 17591.15 | G26: =F26/D26 -> 0.43427518 | Z26: 45901 | AA26: 17912.45 | AB26: 37130.53
B27: Sep | C27: 19156 | D27: 30431.58 | E27: 49587.58 | F27: =D27-C27 -> 11275.58 | G27: =F27/D27 -> 0.37052233 | Z27: 45931 | AA27: 18396.35 | AB27: 28369.59
B28: Total | C28: 368935.91 | D28: 817176.78 | E28: 1186112.7 | F28: =D28-C28 -> 448240.87 | G28: =F28/D28 -> 0.54852375 | Z28: 45962 | AA28: 18523.36 | AB28: 29201.79
Z29: 45992 | AA29: 12548.41 | AB29: 48831.78
Z30: 46023 | AA30: 14793.19 | AB30: 45934.13
Z31: 46054 | AA31: 17780.67 | AB31: 33306.83
Z32: 46082 | AA32: 18342.59 | AB32: 38487.05
Z33: 46113 | AA33: 19296.2 | AB33: 60915.08
Z34: 46143 | AA34: 17758.06 | AB34: 28961.45
Z35: 46174 | AA35: 14106.98 | AB35: 35508.62
Z36: 46204 | AA36: 18351.9 | AB36: 40168.51
Z37: 46235 | AA37: 22915.77 | AB37: 40506.92
Z38: 46266 | AA38: 19156 | AB38: 30431.58

Sheet Expense & Income Analysis
B6: Type | C6: Expense | L6: Type | M6: Income
B8: Categories | C8: Expense Amount | D8: Expense Share | L8: Sub-Categories | M8: Sub-Categories Amount | N8: Income Share
B9: Entertainment | C9: 14702.37 | D9: =C9/$C$16 -> 0.039850743 | L9: Bonus | M9: 168938.74 | N9: =M9/$M$12 -> 0.20673463
B10: Food | C10: 37618.8 | D10: =C10/$C$16 -> 0.10196568 | L10: Freelance | M10: 80412.05 | N10: =M10/$M$12 -> 0.09840227
B11: Health | C11: 18982.55 | D11: =C11/$C$16 -> 0.051452161 | L11: Salary | M11: 567825.99 | N11: =M11/$M$12 -> 0.6948631
B12: Housing | C12: 131986.41 | D12: =C12/$C$16 -> 0.35774888 | L12: Grand Total | M12: 817176.78
B13: Shopping | C13: 74914.88 | D13: =C13/$C$16 -> 0.20305662
B14: Transport | C14: 32064.92 | D14: =C14/$C$16 -> 0.086911898 | BB14: Row Labels | BC14: Sum of Amount | BD14: Income Share
B15: Travel | C15: 58665.98 | D15: =C15/$C$16 -> 0.15901401 | BB15: Bonus | BC15: 168938.74 | BD15: =BC15/$M$12 -> 0.20673463
B16: Total | C16: 368935.91 | BB16: Freelance | BC16: 80412.05 | BD16: =BC16/$M$12 -> 0.09840227
BB17: Salary | BC17: 567825.99 | BD17: =BC17/$M$12 -> 0.6948631
BB24: Row Labels | BC24: Sum of Amount | BD24: Expense Share
BB25: Entertainment | BC25: 14702.37 | BD25: =BC25/$C$16 -> 0.039850743
BB26: Health | BC26: 18982.55 | BD26: =BC26/$C$16 -> 0.051452161
BB27: Transport | BC27: 32064.92 | BD27: =BC27/$C$16 -> 0.086911898
BB28: Food | BC28: 37618.8 | BD28: =BC28/$C$16 -> 0.10196568
BB29: Travel | BC29: 58665.98 | BD29: =BC29/$C$16 -> 0.15901401
BB30: Shopping | BC30: 74914.88 | BD30: =BC30/$C$16 -> 0.20305662
BB31: Housing | BC31: 131986.41 | BD31: =BC31/$C$16 -> 0.35774888

Sheet Dashboard
B3: Personal Finance Analytics Dashboard
B4: Income, Expenses & Savings Overview | 2025–2026
D6: Total Income | F6: Total Expenses | H6: Net Savings | J6: Savings Rate | L6: Income / Expense Ratio | N6: Total Transactions
D7: =Analysis!C6 -> 817176.78 | F7: =Analysis!C8 -> 368935.91 | H7: =Analysis!C10 -> 448240.87 | J7: =Analysis!C12 -> 0.54852375 | L7: =Analysis!C22 -> 2.2149559 | N7: =Analysis!C14 -> 3500
B34: Key Insights
B35: - Salary provides 69.5% of total income.
B37: - Housing accounts for 35.8% of expenses.
B39: - Net savings are $448,241, with a savings rate of 54.85%
